{
	"format_version": "1.10.0",
	"particle_effect": {
		"description": {
			"identifier": "rift:hypnotizer",
			"basic_render_parameters": {
				"material": "particles_alpha",
				"texture": "textures/particle/particles"
			}
		},
		"components": {
			"minecraft:emitter_rate_instant": {
				"num_particles": 100
			},
			"minecraft:emitter_lifetime_once": {
				"active_time": 0.5
			},
			"minecraft:emitter_shape_point": {
				"direction": ["Math.random(-1, 1)", 0, "Math.random(-1, 1)"]
			},
			"minecraft:particle_lifetime_expression": {
				"max_lifetime": "Math.random(0,2)"
			},
			"minecraft:particle_initial_speed": 3,
			"minecraft:particle_motion_dynamic": {},
			"minecraft:particle_appearance_billboard": {
				"size": [0.2, 0.2],
				"facing_camera_mode": "rotate_xyz",
				"uv": {
					"texture_width": 128,
					"texture_height": 128,
					"uv": [56, 0],
					"uv_size": [8, 8]
				}
			},
			"minecraft:particle_appearance_tinting": {
				"color": [1, 0, 0, 1]
			}
		}
	}
}