{
	"format_version": "1.8.0",
	"render_controllers": {
		"controller.render.baryonyx": {
			"geometry": "Geometry.default",
			"arrays": {
				"textures": {
					"Array.skins": [
						"Texture.variant1",
						"Texture.variant2",
						"Texture.variant3",
						"Texture.variant4"
					]
				}
			},
			"textures": [
				"Array.skins[query.variant]"
			],
			"part_visibility": [
				{
					"saddle*": "query.is_saddled",
					"headSaddle*": "query.is_saddled",
					"hiddenBySaddle*": "!query.is_saddled",
					"chest*": "query.is_chested"
				}
			]
		}
	}
}