{
  "format_version": "1.10.0",
  "minecraft:client_entity": {
    "description": {
      "identifier": "rift:stegosaurus",
      "materials": { "default": "entity" },
      "textures": {
        "default": "textures/entity/stegosaurus"
      },
      "geometry": {
        "default": "geometry.stegosaurus"
      },
      "animations": {
        "fight": "controller.animation.stegosaurus.attack",
        "move": "controller.animation.stegosaurus.move",
		"head_movement": "controller.animation.stegosaurus.head_movement",
        "idle": "animation.stegosaurus.idle",
        "walk": "animation.stegosaurus.walk",
        "attack": "animation.stegosaurus.attack",
		"look_at_target": "animation.stegosaurus.look_at_target"
      },
      "scripts": {
        "animate": [
          "move",
          "fight",
		  "head_movement"
        ]
      },
      "render_controllers": [ "controller.render.stegosaurus" ],
      "spawn_egg": {
        "base_color": "#1A6D00",
        "overlay_color": "#FF7C00"
      }
    }
  }
}
